pynumpress/__init__.py
pynumpress/pynumpress.cp310-win_amd64.pyd
pynumpress/version.py
pynumpress-0.0.9.dist-info/LICENSE
pynumpress-0.0.9.dist-info/METADATA
pynumpress-0.0.9.dist-info/WHEEL
pynumpress-0.0.9.dist-info/top_level.txt
pynumpress-0.0.9.dist-info/RECORD
